{
  "schemaVersion": "0.1.0",
  "identifier": "vysamples",
  "title": "Project Vyasa Samples",
  "publications": [
    {
      "id": "vedabase-bg",
      "title": "Bhagavad Gita (Vedabase)",
      "vyviewUrl": "vedabase-bg/vedabase-bg.vyview"
    },
    {
      "id": "vyasa-bg",
      "title": "Bhagavad Gita",
      "vyviewUrl": "vyasa-bg/vyasa-bg.vyview"
    },
    {
      "id": "intimate-note",
      "title": "Intimate Note Sample",
      "vyviewUrl": "intimate-note/intimate-note.vyview"
    },
    {
      "id": "bible",
      "title": "Bible Sample",
      "vyviewUrl": "bible/bible.vyview"
    },
    {
      "id": "minimal",
      "title": "Minimal Sample",
      "vyviewUrl": "minimal/minimal.vyview"
    }
  ]
}